bhdoconvert/__init__.py
BinHexDecOctConversions-1.2.dist-info/LICENSE
BinHexDecOctConversions-1.2.dist-info/METADATA
BinHexDecOctConversions-1.2.dist-info/WHEEL
BinHexDecOctConversions-1.2.dist-info/top_level.txt
BinHexDecOctConversions-1.2.dist-info/RECORD
