Metadata-Version: 2.1
Name: BinHexDecOctConversions
Version: 1.2
Summary: A package that converts between binary, hexadecimal, decimal and octal.
Home-page: https://github.com/TimothyBowen/BinHexDecOctConversions
Author: Timothy Bowen
Author-email: tbowen2k@gmail.com
License: UNKNOWN
Platform: UNKNOWN
Classifier: Programming Language :: Python :: 3
Classifier: License :: OSI Approved :: MIT License
Classifier: Operating System :: OS Independent
